cen/__init__.py
cen/run.py
cen/version.py
cen/callbacks/__init__.py
cen/callbacks/clr.py
cen/configs/config.yaml
cen/configs/encoder/fashion_mnist/cnn.yaml
cen/configs/encoder/imdb/bert.yaml
cen/configs/encoder/imdb/bilstm.yaml
cen/configs/encoder/mnist/cnn.yaml
cen/configs/encoder/physionet/bilstm.yaml
cen/configs/encoder/satellite/identity.yaml
cen/configs/encoder/satellite/mlp.yaml
cen/configs/encoder/support2/identity.yaml
cen/configs/encoder/support2/mlp.yaml
cen/configs/experiment/crossval.yaml
cen/configs/experiment/train_eval.yaml
cen/configs/model/fashion_mnist/baseline.yaml
cen/configs/model/fashion_mnist/cen_affine.yaml
cen/configs/model/fashion_mnist/cen_convex.yaml
cen/configs/model/fashion_mnist/moe.yaml
cen/configs/model/imdb/baseline.yaml
cen/configs/model/imdb/cen_affine.yaml
cen/configs/model/imdb/cen_convex_bow.yaml
cen/configs/model/imdb/cen_convex_tpc.yaml
cen/configs/model/imdb/cen_convex_tpc_semi.yaml
cen/configs/model/imdb/moe.yaml
cen/configs/model/mnist/baseline.yaml
cen/configs/model/mnist/cen_affine.yaml
cen/configs/model/mnist/cen_affine_hog.yaml
cen/configs/model/mnist/cen_affine_pxl.yaml
cen/configs/model/mnist/cen_convex_hog.yaml
cen/configs/model/mnist/cen_convex_pxl.yaml
cen/configs/model/mnist/moe.yaml
cen/configs/model/mnist/moe_hog.yaml
cen/configs/model/mnist/moe_pxl.yaml
cen/configs/model/physionet/baseline.yaml
cen/configs/model/physionet/cen_affine.yaml
cen/configs/model/physionet/cen_convex.yaml
cen/configs/model/physionet/moe.yaml
cen/configs/model/satellite/baseline.yaml
cen/configs/model/satellite/cen_affine.yaml
cen/configs/model/satellite/cen_convex.yaml
cen/configs/model/satellite/moe.yaml
cen/configs/model/support2/baseline.yaml
cen/configs/model/support2/cen_affine.yaml
cen/configs/model/support2/cen_convex.yaml
cen/configs/model/support2/moe.yaml
cen/configs/optimizer/adam.yaml
cen/configs/problem/fashion_mnist.yaml
cen/configs/problem/imdb.yaml
cen/configs/problem/mnist.yaml
cen/configs/problem/physionet.yaml
cen-0.0a2.dist-info/LICENSE
cen-0.0a2.dist-info/METADATA
cen-0.0a2.dist-info/WHEEL
cen-0.0a2.dist-info/top_level.txt
cen-0.0a2.dist-info/RECORD
